{
  "type": "minecraft:generic",
  "pools": [
    {
      "entries": [
        {
          "type": "minecraft:item",
          "name": "minecraft:cod",
          "weight": 4
        },
        {
          "type": "minecraft:item",
          "name": "minecraft:salmon",
          "weight": 3
        },
        {
          "type": "minecraft:item",
          "name": "minecraft:pufferfish",
          "weight": 2
        },
        {
          "type": "minecraft:item",
          "name": "minecraft:tropical_fish",
          "weight": 1
        }
      ],
      "rolls": 1
    }
  ]
}